{"jsonrpc":"2.0","id":0,"result":{"qProp":{"qTitle":"Consumer Sales 122","qSavedInProductVersion":"12.1678.0","qThumbnail":{"qUrl":"/appcontent/04d1f49f-7c3d-4f16-8945-aa49f20d80ab/consumer.png"},"published":false,"publishTime":"2024-06-28T09:43:21.443Z","privileges":["read","update","delete","publish","exportdata","offlineaccess","duplicate"],"description":"See through the eyes of a consumer goods company.  Analyze sales data by sales rep, by region, by product, etc.","dynamicColor":"hsla(74,18%,43%,1)","create":[{"resource":"sheet","canCreate":true},{"resource":"bookmark","canCreate":true},{"resource":"snapshot","canCreate":true},{"resource":"story","canCreate":true},{"resource":"dimension","canCreate":true},{"resource":"measure","canCreate":true},{"resource":"masterobject","canCreate":true},{"resource":"folderconnection","canCreate":true},{"resource":"oledbconnection","canCreate":true},{"resource":"odbcconnection","canCreate":true},{"resource":"internetconnection","canCreate":true},{"resource":"customconnection","canCreate":true}],"stream":{"id":"4fb35a2d-e318-47a8-86ea-1940f5d8c2c6","name":"Live"},"canCreateDataConnections":true}}}