[{"qIsScriptCreated":false,"qInfo":{"qId":"3bfaac37-2735-483a-a877-d9a399f9aaf8","qType":"variable"},"qMetaDef":{},"qName":"name","qNumberPresentation":{"qType":"U","qnDec":10,"qUseThou":0},"qDefinition":"manojs","tags":[]},{"qIsScriptCreated":false,"qInfo":{"qId":"a5ef99be-a050-4dbf-ace8-b3924b958fb6","qType":"variable"},"qMetaDef":{},"qName":"crossAppsSearchEnabled","qNumberPresentation":{"qType":"U","qnDec":10,"qUseThou":0},"qDefinition":"1","tags":[]},{"qIsScriptCreated":false,"qInfo":{"qId":"79bdfc66-fc8b-4be8-a543-57fef13418ee","qType":"variable"},"qMetaDef":{},"qName":"VizlibFinanceReportAfjhtUm","qNumberPresentation":{"qType":"U","qnDec":10,"qUseThou":0},"qIncludeInBookmark":true},{"qIsScriptCreated":false,"qInfo":{"qId":"cb6eabea-e6b0-4983-8ab6-89de8ffb9e0e","qType":"variable"},"qMetaDef":{},"qName":"VizlibFinanceReportBeJXKY","qNumberPresentation":{"qType":"U","qnDec":10,"qUseThou":0},"qIncludeInBookmark":true},{"qIsScriptCreated":false,"qInfo":{"qId":"3566dd76-21f6-4268-b7a0-387b41eb1865","qType":"variable"},"qMetaDef":{},"qName":"vDisplay","qNumberPresentation":{"qType":"U","qnDec":10,"qUseThou":0},"qDefinition":"=if(isnull(State),'none','block')","tags":[]},{"qIsScriptCreated":false,"qInfo":{"qId":"fa7e10b8-76b5-4d71-a0af-16aa65769ebb","qType":"variable"},"qMetaDef":{},"qName":"vIndex","qNumberPresentation":{"qType":"U","qnDec":10,"qUseThou":0},"qDefinition":"0","tags":[]},{"qIsScriptCreated":false,"qInfo":{"qId":"d2cabffc-d24e-4896-bc45-f273d88954b8","qType":"variable"},"qMetaDef":{},"qName":"vField","qNumberPresentation":{"qType":"U","qnDec":10,"qUseThou":0},"qDefinition":"=if($(vIndex)=0, 'Month',' Year')","tags":[]},{"qIsScriptCreated":false,"qInfo":{"qId":"07418893-6cf4-4692-9c9b-c11993ad4536","qType":"variable"},"qMetaDef":{},"qName":"LastUpdatedDataKey","qNumberPresentation":{"qType":"U","qnDec":10,"qUseThou":0},"qDefinition":"2"},{"qIsScriptCreated":false,"qInfo":{"qId":"bc7cf62c-cfee-49d0-bd6d-6f245c35a9c7","qType":"variable"},"qMetaDef":{},"qName":"LastUpdatedDataKEY","qNumberPresentation":{"qType":"U","qnDec":10,"qUseThou":0},"qDefinition":"1"},{"qIsScriptCreated":true,"qInfo":{"qId":"88ca686e-6be0-443c-85ad-48027febb68d","qType":"variable"},"qMetaDef":{},"qName":"ErrorMode","qNumberPresentation":{"qType":"U","qnDec":10,"qUseThou":0},"qDefinition":"1"},{"qIsScriptCreated":true,"qInfo":{"qId":"e660db7d-d025-4e05-9d5d-b91386b59aea","qType":"variable"},"qMetaDef":{},"qName":"StripComments","qNumberPresentation":{"qType":"U","qnDec":10,"qUseThou":0},"qDefinition":"1"},{"qIsScriptCreated":true,"qInfo":{"qId":"47a15c46-f2f1-4caf-aa9e-edac7a7572fb","qType":"variable"},"qMetaDef":{},"qName":"OpenUrlTimeout","qNumberPresentation":{"qType":"U","qnDec":10,"qUseThou":0},"qDefinition":"86400"},{"qIsScriptCreated":true,"qInfo":{"qId":"a4d00933-be70-4bbf-8f83-78e1ac04b793","qType":"variable"},"qMetaDef":{},"qName":"ScriptError","qNumberPresentation":{"qType":"U","qnDec":10,"qUseThou":0}},{"qIsScriptCreated":true,"qInfo":{"qId":"b42a8f44-03d6-4977-b495-c76f9a8d4389","qType":"variable"},"qMetaDef":{},"qName":"ScriptErrorCount","qNumberPresentation":{"qType":"U","qnDec":10,"qUseThou":0},"qDefinition":"0"},{"qIsScriptCreated":true,"qInfo":{"qId":"9a4a3679-ba3a-4d92-a937-02321823f2b4","qType":"variable"},"qMetaDef":{},"qName":"ScriptErrorList","qNumberPresentation":{"qType":"U","qnDec":10,"qUseThou":0}},{"qIsScriptCreated":true,"qInfo":{"qId":"0a4e2155-a208-4acf-986a-6f38142db931","qType":"variable"},"qMetaDef":{},"qName":"ThousandSep","qNumberPresentation":{"qType":"U","qnDec":10,"qUseThou":0},"qDefinition":","},{"qIsScriptCreated":true,"qInfo":{"qId":"2019feda-6374-476f-abc7-a463b3a48d9c","qType":"variable"},"qMetaDef":{},"qName":"DecimalSep","qNumberPresentation":{"qType":"U","qnDec":10,"qUseThou":0},"qDefinition":"."},{"qIsScriptCreated":true,"qInfo":{"qId":"789b5b51-4614-458c-9faf-b6f7a42a32dd","qType":"variable"},"qMetaDef":{},"qName":"MoneyThousandSep","qNumberPresentation":{"qType":"U","qnDec":10,"qUseThou":0},"qDefinition":","},{"qIsScriptCreated":true,"qInfo":{"qId":"6ec5a950-8674-46d5-a323-3fa88927b20d","qType":"variable"},"qMetaDef":{},"qName":"MoneyDecimalSep","qNumberPresentation":{"qType":"U","qnDec":10,"qUseThou":0},"qDefinition":"."},{"qIsScriptCreated":true,"qInfo":{"qId":"ceb95b96-8159-4ee6-b5d1-8d68b03f320f","qType":"variable"},"qMetaDef":{},"qName":"MoneyFormat","qNumberPresentation":{"qType":"U","qnDec":10,"qUseThou":0},"qDefinition":"$#,##0.00;($#,##0.00)"},{"qIsScriptCreated":true,"qInfo":{"qId":"4de0a6e7-290c-48d7-9378-516c88b04869","qType":"variable"},"qMetaDef":{},"qName":"TimeFormat","qNumberPresentation":{"qType":"U","qnDec":10,"qUseThou":0},"qDefinition":"h:mm:ss TT"},{"qIsScriptCreated":true,"qInfo":{"qId":"c77188ac-d011-4318-a25f-f1992cc49d01","qType":"variable"},"qMetaDef":{},"qName":"DateFormat","qNumberPresentation":{"qType":"U","qnDec":10,"qUseThou":0},"qDefinition":"M/D/YYYY"},{"qIsScriptCreated":true,"qInfo":{"qId":"4c6775d2-2f10-44ca-be26-956702f07ef7","qType":"variable"},"qMetaDef":{},"qName":"TimestampFormat","qNumberPresentation":{"qType":"U","qnDec":10,"qUseThou":0},"qDefinition":"M/D/YYYY h:mm:ss[.fff] TT"},{"qIsScriptCreated":true,"qInfo":{"qId":"84f36b93-3355-4909-ae98-10f00128ee23","qType":"variable"},"qMetaDef":{},"qName":"MonthNames","qNumberPresentation":{"qType":"U","qnDec":10,"qUseThou":0},"qDefinition":"Jan;Feb;Mar;Apr;May;Jun;Jul;Aug;Sep;Oct;Nov;Dec"},{"qIsScriptCreated":true,"qInfo":{"qId":"504dd66b-08c4-46be-8fe8-87f5136640c8","qType":"variable"},"qMetaDef":{},"qName":"DayNames","qNumberPresentation":{"qType":"U","qnDec":10,"qUseThou":0},"qDefinition":"Mon;Tue;Wed;Thu;Fri;Sat;Sun"},{"qIsScriptCreated":true,"qInfo":{"qId":"5530ec85-71a1-4eac-b7a3-58f3595aa4ae","qType":"variable"},"qMetaDef":{},"qName":"LastUpdatedDataID","qNumberPresentation":{"qType":"U","qnDec":10,"qUseThou":0},"qDefinition":"38"}]