[{"qInfo":{"qId":"158f0180-ec18-4771-8bb5-c245e75fa1d2","qType":"bookmark"},"qMeta":{"title":"Sheet 4","description":"","createdDate":"2024-05-09T10:29:00.338Z","modifiedDate":"2024-05-09T10:29:00.338Z","published":false,"publishTime":"1753-01-01T00:00:00.000Z","approved":false,"owner":{"id":"5d9d879d-fa4b-4922-8e8d-2abeb791ca6e","userId":"rajasekarv","userDirectory":"GAIN-INSIGHTS","userDirectoryConnectorName":"","name":"rajasekarv","privileges":null},"qSize":-1,"sourceObject":"","draftObject":"","privileges":["read","update","delete","exportdata","publish","approve"],"isExtended":false},"qData":{"qBookmark":{"qStateData":[{"qStateName":"$","qFieldItems":[{"qDef":{"qName":"Branch","qType":"PRESENT"},"qSelectInfo":{"qRangeLo":"NaN","qRangeHi":"NaN","qNumberFormat":{"qType":"U","qnDec":10,"qUseThou":0},"qRangeInfo":[],"qContinuousRangeInfo":[]},"qValues":[],"qExcludedValues":[]}]},{"qStateName":"State_BarChart","qFieldItems":[]},{"qStateName":"State_LineChart","qFieldItems":[]},{"qStateName":"State_StackedBar","qFieldItems":[]},{"qStateName":"KPI_State","qFieldItems":[]}],"qUtcModifyTime":45430.48787037037,"qVariableItems":[],"qPatches":[]},"qSheetId":"21d229f2-d102-4a6c-9bce-d0c959c00983","qExpression":"<Branch={'A'}>"}},{"qInfo":{"qId":"4464761f-670e-4ced-8e8e-fbb95a7661e1","qType":"bookmark"},"qMeta":{"title":"Raju","description":"","createdDate":"2024-05-09T11:07:07.422Z","modifiedDate":"2024-05-09T11:07:07.422Z","published":false,"publishTime":"1753-01-01T00:00:00.000Z","approved":false,"owner":{"id":"5d9d879d-fa4b-4922-8e8d-2abeb791ca6e","userId":"rajasekarv","userDirectory":"GAIN-INSIGHTS","userDirectoryConnectorName":"","name":"rajasekarv","privileges":null},"qSize":-1,"sourceObject":"","draftObject":"","privileges":["read","update","delete","exportdata","publish","approve"],"isExtended":false},"qData":{"qBookmark":{"qStateData":[{"qStateName":"$","qFieldItems":[{"qDef":{"qName":"Product line","qType":"PRESENT"},"qSelectInfo":{"qRangeLo":"NaN","qRangeHi":"NaN","qNumberFormat":{"qType":"U","qnDec":10,"qUseThou":0},"qRangeInfo":[],"qContinuousRangeInfo":[]},"qValues":[],"qExcludedValues":[]},{"qDef":{"qName":"Date","qType":"PRESENT"},"qSelectInfo":{"qRangeLo":"NaN","qRangeHi":"NaN","qNumberFormat":{"qType":"U","qnDec":10,"qUseThou":0},"qRangeInfo":[],"qContinuousRangeInfo":[]},"qValues":[],"qExcludedValues":[]}]},{"qStateName":"State_BarChart","qFieldItems":[]},{"qStateName":"State_LineChart","qFieldItems":[]},{"qStateName":"State_StackedBar","qFieldItems":[]},{"qStateName":"KPI_State","qFieldItems":[]}],"qUtcModifyTime":45430.48787037037,"qVariableItems":[],"qPatches":[]},"qSheetId":"bc01dae6-ea59-4154-ab23-afa8648aff97","qExpression":"<[Product line]={'Sports and travel','Electronic accessories','Food and beverages'},Date={'02/01/2019','03/01/2019','04/01/2019','18/01/2019'}>"}},{"qInfo":{"qId":"502f107e-2965-4be7-a30d-5b5439879e3c","qType":"bookmark"},"qMeta":{"title":"Sheet 3(II)","description":"","createdDate":"2024-05-09T10:29:00.338Z","modifiedDate":"2024-05-09T10:29:00.338Z","published":false,"publishTime":"1753-01-01T00:00:00.000Z","approved":false,"owner":{"id":"5d9d879d-fa4b-4922-8e8d-2abeb791ca6e","userId":"rajasekarv","userDirectory":"GAIN-INSIGHTS","userDirectoryConnectorName":"","name":"rajasekarv","privileges":null},"qSize":-1,"sourceObject":"","draftObject":"","privileges":["read","update","delete","exportdata","publish","approve"],"isExtended":false},"qData":{"qBookmark":{"qStateData":[{"qStateName":"$","qFieldItems":[{"qDef":{"qName":"Customer type","qType":"PRESENT"},"qSelectInfo":{"qRangeLo":"NaN","qRangeHi":"NaN","qNumberFormat":{"qType":"U","qnDec":10,"qUseThou":0},"qRangeInfo":[],"qContinuousRangeInfo":[]},"qValues":[],"qExcludedValues":[]},{"qDef":{"qName":"Month","qType":"PRESENT"},"qSelectInfo":{"qRangeLo":"NaN","qRangeHi":"NaN","qNumberFormat":{"qType":"U","qnDec":10,"qUseThou":0},"qRangeInfo":[],"qContinuousRangeInfo":[]},"qValues":[],"qExcludedValues":[]}]},{"qStateName":"State_BarChart","qFieldItems":[]},{"qStateName":"State_LineChart","qFieldItems":[]},{"qStateName":"State_StackedBar","qFieldItems":[]},{"qStateName":"KPI_State","qFieldItems":[]}],"qUtcModifyTime":45430.48787037037,"qVariableItems":[],"qPatches":[]},"qSheetId":"f811ea4a-a808-4354-862e-2114db77ede2","qExpression":"<[Customer type]={'Normal'},Month={'Mar 2019'}>"}},{"qInfo":{"qId":"588d66c0-6c43-4f2f-91cd-4aa18b75ebc1","qType":"bookmark"},"qMeta":{"title":"Sheet 2(II)","description":"","createdDate":"2024-05-09T10:29:00.338Z","modifiedDate":"2024-05-09T10:29:00.338Z","published":false,"publishTime":"1753-01-01T00:00:00.000Z","approved":false,"owner":{"id":"5d9d879d-fa4b-4922-8e8d-2abeb791ca6e","userId":"rajasekarv","userDirectory":"GAIN-INSIGHTS","userDirectoryConnectorName":"","name":"rajasekarv","privileges":null},"qSize":-1,"sourceObject":"","draftObject":"","privileges":["read","update","delete","exportdata","publish","approve"],"isExtended":false},"qData":{"qBookmark":{"qStateData":[{"qStateName":"$","qFieldItems":[{"qDef":{"qName":"Branch","qType":"PRESENT"},"qSelectInfo":{"qRangeLo":"NaN","qRangeHi":"NaN","qNumberFormat":{"qType":"U","qnDec":10,"qUseThou":0},"qRangeInfo":[],"qContinuousRangeInfo":[]},"qValues":[],"qExcludedValues":[]},{"qDef":{"qName":"Month","qType":"PRESENT"},"qSelectInfo":{"qRangeLo":"NaN","qRangeHi":"NaN","qNumberFormat":{"qType":"U","qnDec":10,"qUseThou":0},"qRangeInfo":[],"qContinuousRangeInfo":[]},"qValues":[],"qExcludedValues":[]}]},{"qStateName":"State_BarChart","qFieldItems":[]},{"qStateName":"State_LineChart","qFieldItems":[]},{"qStateName":"State_StackedBar","qFieldItems":[]},{"qStateName":"KPI_State","qFieldItems":[]}],"qUtcModifyTime":45430.48787037037,"qVariableItems":[],"qPatches":[]},"qSheetId":"6993e012-f179-423a-aa32-4266aa160f2e","qExpression":"<Branch={'A'},Month={'Mar 2019'}>"}},{"qInfo":{"qId":"a4d3c4ca-8042-43eb-838e-b7a1b497977f","qType":"bookmark"},"qMeta":{"title":"Sheet1","description":"","createdDate":"2024-05-09T10:29:00.338Z","modifiedDate":"2024-05-09T10:29:00.338Z","published":false,"publishTime":"1753-01-01T00:00:00.000Z","approved":false,"owner":{"id":"5d9d879d-fa4b-4922-8e8d-2abeb791ca6e","userId":"rajasekarv","userDirectory":"GAIN-INSIGHTS","userDirectoryConnectorName":"","name":"rajasekarv","privileges":null},"qSize":-1,"sourceObject":"","draftObject":"","privileges":["read","update","delete","exportdata","publish","approve"],"isExtended":false},"qData":{"qBookmark":{"qStateData":[{"qStateName":"$","qFieldItems":[{"qDef":{"qName":"Branch","qType":"PRESENT"},"qSelectInfo":{"qRangeLo":"NaN","qRangeHi":"NaN","qNumberFormat":{"qType":"U","qnDec":10,"qUseThou":0},"qRangeInfo":[],"qContinuousRangeInfo":[]},"qValues":[],"qExcludedValues":[]}]},{"qStateName":"State_BarChart","qFieldItems":[]},{"qStateName":"State_LineChart","qFieldItems":[]},{"qStateName":"State_StackedBar","qFieldItems":[]},{"qStateName":"KPI_State","qFieldItems":[]}],"qUtcModifyTime":45430.48787037037,"qVariableItems":[],"qPatches":[]},"qSheetId":"bc01dae6-ea59-4154-ab23-afa8648aff97","qExpression":"<Branch={'A'}>"}},{"qInfo":{"qId":"c14680fd-a903-4e7b-8c22-b71aa626bfcf","qType":"bookmark"},"qMeta":{"title":"Sheet 2(I)","description":"","createdDate":"2024-05-09T10:29:00.338Z","modifiedDate":"2024-05-09T10:29:00.338Z","published":false,"publishTime":"1753-01-01T00:00:00.000Z","approved":false,"owner":{"id":"5d9d879d-fa4b-4922-8e8d-2abeb791ca6e","userId":"rajasekarv","userDirectory":"GAIN-INSIGHTS","userDirectoryConnectorName":"","name":"rajasekarv","privileges":null},"qSize":-1,"sourceObject":"","draftObject":"","privileges":["read","update","delete","exportdata","publish","approve"],"isExtended":false},"qData":{"qBookmark":{"qStateData":[{"qStateName":"$","qFieldItems":[{"qDef":{"qName":"Month","qType":"PRESENT"},"qSelectInfo":{"qRangeLo":"NaN","qRangeHi":"NaN","qNumberFormat":{"qType":"U","qnDec":10,"qUseThou":0},"qRangeInfo":[],"qContinuousRangeInfo":[]},"qValues":[],"qExcludedValues":[]}]},{"qStateName":"State_BarChart","qFieldItems":[]},{"qStateName":"State_LineChart","qFieldItems":[]},{"qStateName":"State_StackedBar","qFieldItems":[]},{"qStateName":"KPI_State","qFieldItems":[]}],"qUtcModifyTime":45430.48787037037,"qVariableItems":[],"qPatches":[]},"qSheetId":"6993e012-f179-423a-aa32-4266aa160f2e","qExpression":"<Month={'Mar 2019'}>"}},{"qInfo":{"qId":"f65a909c-de5d-4657-af02-aeda63a60ba5","qType":"bookmark"},"qMeta":{"title":"Demo","description":"","createdDate":"2024-05-09T10:29:00.338Z","modifiedDate":"2024-05-09T10:29:00.338Z","published":false,"publishTime":"1753-01-01T00:00:00.000Z","approved":false,"owner":{"id":"5d9d879d-fa4b-4922-8e8d-2abeb791ca6e","userId":"rajasekarv","userDirectory":"GAIN-INSIGHTS","userDirectoryConnectorName":"","name":"rajasekarv","privileges":null},"qSize":-1,"sourceObject":"","draftObject":"","privileges":["read","update","delete","exportdata","publish","approve"],"isExtended":false},"qData":{"qBookmark":{"qStateData":[{"qStateName":"$","qFieldItems":[{"qDef":{"qName":"Branch","qType":"PRESENT"},"qSelectInfo":{"qRangeLo":"NaN","qRangeHi":"NaN","qNumberFormat":{"qType":"U","qnDec":10,"qUseThou":0},"qRangeInfo":[],"qContinuousRangeInfo":[]},"qValues":[],"qExcludedValues":[]}]},{"qStateName":"State_BarChart","qFieldItems":[]},{"qStateName":"State_LineChart","qFieldItems":[]},{"qStateName":"State_StackedBar","qFieldItems":[]},{"qStateName":"KPI_State","qFieldItems":[]}],"qUtcModifyTime":45430.48788194444,"qVariableItems":[],"qPatches":[]},"qSheetId":"bc01dae6-ea59-4154-ab23-afa8648aff97","qExpression":"<Branch={'A'}>"}},{"qInfo":{"qId":"f7288dd2-ea3b-4f18-81b8-efa015117601","qType":"bookmark"},"qMeta":{"title":"Sheet 3(I)","description":"","createdDate":"2024-05-09T10:29:00.338Z","modifiedDate":"2024-05-09T10:29:00.338Z","published":false,"publishTime":"1753-01-01T00:00:00.000Z","approved":false,"owner":{"id":"5d9d879d-fa4b-4922-8e8d-2abeb791ca6e","userId":"rajasekarv","userDirectory":"GAIN-INSIGHTS","userDirectoryConnectorName":"","name":"rajasekarv","privileges":null},"qSize":-1,"sourceObject":"","draftObject":"","privileges":["read","update","delete","exportdata","publish","approve"],"isExtended":false},"qData":{"qBookmark":{"qStateData":[{"qStateName":"$","qFieldItems":[{"qDef":{"qName":"Month","qType":"PRESENT"},"qSelectInfo":{"qRangeLo":"NaN","qRangeHi":"NaN","qNumberFormat":{"qType":"U","qnDec":10,"qUseThou":0},"qRangeInfo":[],"qContinuousRangeInfo":[]},"qValues":[],"qExcludedValues":[]}]},{"qStateName":"State_BarChart","qFieldItems":[]},{"qStateName":"State_LineChart","qFieldItems":[]},{"qStateName":"State_StackedBar","qFieldItems":[]},{"qStateName":"KPI_State","qFieldItems":[]}],"qUtcModifyTime":45430.48788194444,"qVariableItems":[],"qPatches":[]},"qSheetId":"f811ea4a-a808-4354-862e-2114db77ede2","qExpression":"<Month={'Mar 2019'}>"}}]