[{"qInfo":{"qId":"631bbf06-5da0-4075-8415-589f0f9bc700","qType":"bookmark"},"qMeta":{"privileges":["read","update","delete","publish","change_owner"],"title":"Bookmark 1","description":"","isExtended":true},"qData":{"qBookmark":{"qStateData":[{"qStateName":"$","qFieldItems":[{"qDef":{"qName":"Product line","qType":"PRESENT"},"qSelectInfo":{"qRangeLo":"NaN","qRangeHi":"NaN","qNumberFormat":{"qType":"U","qnDec":10,"qUseThou":0},"qRangeInfo":[],"qContinuousRangeInfo":[]},"qValues":[],"qExcludedValues":[]},{"qDef":{"qName":"Date","qType":"PRESENT"},"qSelectInfo":{"qRangeLo":"NaN","qRangeHi":"NaN","qNumberFormat":{"qType":"U","qnDec":10,"qUseThou":0},"qRangeInfo":[],"qContinuousRangeInfo":[]},"qValues":[],"qExcludedValues":[]}]},{"qStateName":"KPI_State","qFieldItems":[]},{"qStateName":"State_BarChart","qFieldItems":[]},{"qStateName":"State_StackedBar","qFieldItems":[]},{"qStateName":"State_LineChart","qFieldItems":[]}],"qVariableItems":[{"qName":"_gitoqlokMetaData_variable","qValue":{"qText":"{\"masterId\":\"e9f266a8-602d-4246-a8ca-8896d5223306\",\"infoByServerType\":{},\"updatedAt\":1716010095281}","qNumber":"NaN"}},{"qName":"Variable_Input","qValue":{"qText":"aggr([Product line]={<${'Fashion accessories'}>},[Product line])","qNumber":"NaN"}},{"qName":"vCredit_Card","qValue":{"qText":"(count({$<Payment = {\"Credit card\"},Month = {\"Mar 2019\"}>}Payment)- count({$<Payment = {\"Credit card\"},Month = {\"Feb 2019\"}>}Payment))/count({$<Payment = {\"Credit card\"},Month = {\"Feb 2019\"}>}Payment)","qNumber":"NaN"}},{"qName":"vCurrent_Margin","qValue":{"qText":"sum({$<Date ={\">=$(=AddMonths(min(Date),2))\"}>}[gross income] )","qNumber":"NaN"}},{"qName":"vCash","qValue":{"qText":"(count({$<Payment = {\"Cash\"},Month = {\"Mar 2019\"}>}Payment)- count({$<Payment = {\"Cash\"},Month = {\"Feb 2019\"}>}Payment))/count({$<Payment = {\"Cash\"},Month = {\"Feb 2019\"}>}Payment)","qNumber":"NaN"}},{"qName":"vCount_PreviousID","qValue":{"qText":"Count(distinct {$<Month = {\"Feb 2019\"}>}[Invoice ID])\r\n\n//,[Product line]={'$(vAttribute)'}","qNumber":"NaN"}},{"qName":"vCurrentMonth_Tax","qValue":{"qText":"sum({$<Month = {\"Mar 2019\"}>}[Tax 5%])","qNumber":"NaN"}},{"qName":"vFemale_GrossIncome","qValue":{"qText":"Sum({$<Gender = {'Female'},Date = {\">=$(=AddMonths(min(Date),2))\"}>}  [gross income])","qNumber":"NaN"}},{"qName":"vDifference","qValue":{"qText":"(sum({$<Month = {\"Mar 2019\"}>}cogs)-sum({$<Date = {\">=$(=AddMonths(min(Date),1))<=$(=AddMonths(max(Date),-1))\"} >}cogs ))/sum({$<Date = {\">=$(=AddMonths(min(Date),1))<=$(=AddMonths(max(Date),-1))\"} >}cogs )","qNumber":"NaN"}},{"qName":"vCount_CurrentID","qValue":{"qText":"Count(distinct {$<Month = {\"Mar 2019\"}>}[Invoice ID])\r\n\n","qNumber":"NaN"}},{"qName":"vHide","qValue":{"qText":"0","qIsNumeric":true,"qNumber":0}},{"qName":"vEwallent","qValue":{"qText":"(count({$<Payment = {\"Ewallet\"},Month = {\"Mar 2019\"}>}Payment)- count({$<Payment = {\"Ewallet\"},Month = {\"Feb 2019\"}>}Payment))/count({$<Payment = {\"Ewallet\"},Month = {\"Feb 2019\"}>}Payment)","qNumber":"NaN"}},{"qName":"vPreviousMon_Quantity","qValue":{"qText":"sum({$<Date = {\">=$(=AddMonths(min(Date),1))<=$(=AddMonths(max(Date),-1))\"} >}Quantity )","qNumber":"NaN"}},{"qName":"vCurrent_TotalRev","qValue":{"qText":"sum({$<Month = {\"Mar 2019\"}>}Total )","qNumber":"NaN"}},{"qName":"vDifference_Previous_cogs","qValue":{"qText":"(sum({$<Date = {\">=$(=AddMonths(min(Date),1))<=$(=AddMonths(max(Date),-1))\"} >}cogs ) -sum({$<Date = {\">=$(=AddMonths(min(Date),0))<=$(=date(AddMonths(max(Date),-2)+1))\"} >}cogs )) /sum({$<Date = {\">=$(=AddMonths(min(Date),0))<=$(=date(AddMonths(max(Date),-2)+1))\"} >}cogs )\r\n","qNumber":"NaN"}},{"qName":"vPreviousMonth_CreditCard","qValue":{"qText":"(count({$<Payment = {\"Credit card\"},Month = {\"Feb 2019\"}>}Payment)- count({$<Payment = {\"Credit card\"},Month = {\"Jan 2019\"}>}Payment))/count({$<Payment = {\"Credit card\"},Month = {\"Jan 2019\"}>}Payment)","qNumber":"NaN"}},{"qName":"vPreviousMonth_Cash","qValue":{"qText":"(count({$<Payment = {\"Cash\"},Month = {\"Feb 2019\"}>}Payment)- count({$<Payment = {\"Cash\"},Month = {\"Jan 2019\"}>}Payment))/count({$<Payment = {\"Cash\"},Month = {\"Jan 2019\"}>}Payment)","qNumber":"NaN"}},{"qName":"vMale_GrossIncome","qValue":{"qText":"Sum({$<Gender = {'Male'},Date = {\">=$(=AddMonths(min(Date),2))\"}>}  [gross income])\r\n\n","qNumber":"NaN"}},{"qName":"vGrosss_Margin_Percentage","qValue":{"qText":"(sum({$<Date ={\">=$(=AddMonths(min(Date),2))\"}>}[gross margin percentage] )-sum({$<Date = {\">=$(=AddMonths(min(Date),1))<=$(=AddMonths(max(Date),-1))\"} >}[gross margin percentage] ))/ sum({$<Date = {\">=$(=AddMonths(min(Date),1))<=$(=AddMonths(max(Date),-1))\"} >}[gross margin percentage] )","qNumber":"NaN"}},{"qName":"vPrevious_Margin","qValue":{"qText":"sum({$<Date = {\">=$(=AddMonths(min(Date),1))<=$(=AddMonths(max(Date),-1))\"} >} [gross income] )","qNumber":"NaN"}},{"qName":"vQuantity","qValue":{"qText":"sum({$<Date ={\">=$(=AddMonths(min(Date),2))\"}>}Quantity ) ","qNumber":"NaN"}},{"qName":"vPrevious_Tax","qValue":{"qText":"sum({$<Month = { \"Feb 2019\"}>}[Tax 5%])","qNumber":"NaN"}},{"qName":"vPrevious_TotalRev","qValue":{"qText":"sum({$<Month = {\"Feb 2019\"} >} Total )","qNumber":"NaN"}},{"qName":"vPreviousMonth_Ewallet","qValue":{"qText":"(count({$<Payment = {\"Ewallet\"},Month = {\"Feb 2019\"}>}Payment)- count({$<Payment = {\"Ewallet\"},Month = {\"Jan 2019\"}>}Payment))/count({$<Payment = {\"Ewallet\"},Month = {\"Jan 2019\"}>}Payment)","qNumber":"NaN"}}],"qPatches":[],"qCyclicGroupStates":[],"qGroupStates":[]},"qSheetId":"bc01dae6-ea59-4154-ab23-afa8648aff97","qExpression":"<[Product line]={'Electronic accessories','Fashion accessories'},Date={'21/02/2019','04/03/2019'}>"}},{"qInfo":{"qId":"b306a09d-29d3-4983-af10-fcda4b62ab37","qType":"bookmark"},"qMeta":{"privileges":["read","update","delete","publish","change_owner"],"title":"Bookmark 2","description":"","isExtended":false},"qData":{"qBookmark":{"qStateData":[{"qStateName":"$","qFieldItems":[{"qDef":{"qName":"Product line","qType":"PRESENT"},"qSelectInfo":{"qRangeLo":"NaN","qRangeHi":"NaN","qNumberFormat":{"qType":"U","qnDec":10,"qUseThou":0},"qRangeInfo":[],"qContinuousRangeInfo":[]},"qValues":[],"qExcludedValues":[]},{"qDef":{"qName":"Date","qType":"PRESENT"},"qSelectInfo":{"qRangeLo":"NaN","qRangeHi":"NaN","qNumberFormat":{"qType":"U","qnDec":10,"qUseThou":0},"qRangeInfo":[],"qContinuousRangeInfo":[]},"qValues":[],"qExcludedValues":[]}]},{"qStateName":"KPI_State","qFieldItems":[]},{"qStateName":"State_BarChart","qFieldItems":[]},{"qStateName":"State_StackedBar","qFieldItems":[]},{"qStateName":"State_LineChart","qFieldItems":[]}],"qVariableItems":[],"qPatches":[],"qCyclicGroupStates":[],"qGroupStates":[]},"qSheetId":"bc01dae6-ea59-4154-ab23-afa8648aff97","qExpression":"<[Product line]={'Health and beauty','Electronic accessories','Fashion accessories','Food and beverages'},Date={'02/01/2019','05/01/2019','06/01/2019','21/02/2019','04/03/2019'}>"}}]